{
  "type": "mod_science:abyss",
  "generator": {
    "biome_source": {
      "humidity_noise": {
        "firstOctave": -7,
        "amplitudes": [
          1.0,
          1.0
        ]
      },
      "altitude_noise": {
        "firstOctave": -7,
        "amplitudes": [
          1.0,
          1.0
        ]
      },
      "weirdness_noise": {
        "firstOctave": -7,
        "amplitudes": [
          1.0,
          1.0
        ]
      },
      "seed": 876543210,
      "biomes": [
        {
          "parameters": {
            "altitude": 0.0,
            "weirdness": 0.0,
            "offset": 0.175,
            "temperature": -0.5,
            "humidity": 0.0
          },
          "biome": "mod_science:abyss"
        }
      ],
      "temperature_noise": {
        "firstOctave": -7,
        "amplitudes": [
          1.0,
          1.0
        ]
      },
      "type": "minecraft:multi_noise"
    },
    "seed": 876543210,
    "settings": "mod_science:abyss",
    "type": "minecraft:noise"
  }
}